BetterErrorMessages-0.4.dist-info/DESCRIPTION.rst
BetterErrorMessages-0.4.dist-info/METADATA
BetterErrorMessages-0.4.dist-info/RECORD
BetterErrorMessages-0.4.dist-info/WHEEL
BetterErrorMessages-0.4.dist-info/metadata.json
BetterErrorMessages-0.4.dist-info/top_level.txt
didyoumean/__init__.py
didyoumean/didyoumean_api.py
didyoumean/didyoumean_api_tests.py
didyoumean/didyoumean_common_tests.py
didyoumean/didyoumean_internal.py
didyoumean/didyoumean_internal_tests.py
didyoumean/didyoumean_re.py
didyoumean/didyoumean_re_tests.py
didyoumean/didyoumean_sugg_tests.py
didyoumean/readme_examples.py
